LICENSE
README.md
pdfslim.py
setup.cfg
setup.py
pdfslim.egg-info/PKG-INFO
pdfslim.egg-info/SOURCES.txt
pdfslim.egg-info/dependency_links.txt
pdfslim.egg-info/entry_points.txt
pdfslim.egg-info/top_level.txt